xpartition/__init__.py
xpartition/xarray_utils.py
xpartition/xpartition.py
xpartition-2025.3.0.dist-info/LICENSE
xpartition-2025.3.0.dist-info/METADATA
xpartition-2025.3.0.dist-info/WHEEL
xpartition-2025.3.0.dist-info/top_level.txt
xpartition-2025.3.0.dist-info/RECORD
